lansync/__init__.py
lansync/guestfs.py
lansync/lansync.py
lansync/settings.py
lansync/utilities.py
lansync-0.0.1.data/scripts/lansync
lansync-0.0.1.dist-info/LICENSE
lansync-0.0.1.dist-info/METADATA
lansync-0.0.1.dist-info/WHEEL
lansync-0.0.1.dist-info/top_level.txt
lansync-0.0.1.dist-info/RECORD
