Metadata-Version: 2.1
Name: lansync
Version: 0.0.1
Summary: Make file sharing easier
Home-page: https://github.com/ViktorBarzin/lansync
Author: Viktor Barzin
Author-email: vbarzin@gmail.com
License: UNKNOWN
Platform: UNKNOWN
Classifier: Programming Language :: Python :: 3
Classifier: License :: OSI Approved :: MIT License
Classifier: Operating System :: OS Independent
Requires-Dist: sshpubkeys
